ooodev/__init__.py
ooodev/adapter/__init__.py
ooodev/adapter/adapter_base.py
ooodev/adapter/awt/__init__.py
ooodev/adapter/awt/action_events.py
ooodev/adapter/awt/action_listener.py
ooodev/adapter/awt/adjustment_events.py
ooodev/adapter/awt/adjustment_listener.py
ooodev/adapter/awt/control_partial.py
ooodev/adapter/awt/dialog2_partial.py
ooodev/adapter/awt/dialog_partial.py
ooodev/adapter/awt/enhanced_mouse_click_events.py
ooodev/adapter/awt/enhanced_mouse_click_handler.py
ooodev/adapter/awt/focus_events.py
ooodev/adapter/awt/focus_listener.py
ooodev/adapter/awt/grid/__init__.py
ooodev/adapter/awt/grid/grid_column_events.py
ooodev/adapter/awt/grid/grid_column_listener.py
ooodev/adapter/awt/grid/grid_data_events.py
ooodev/adapter/awt/grid/grid_data_listener.py
ooodev/adapter/awt/grid/grid_selection_events.py
ooodev/adapter/awt/grid/grid_selection_listener.py
ooodev/adapter/awt/index_container_comp.py
ooodev/adapter/awt/item_events.py
ooodev/adapter/awt/item_list_events.py
ooodev/adapter/awt/item_list_listener.py
ooodev/adapter/awt/item_listener.py
ooodev/adapter/awt/key_events.py
ooodev/adapter/awt/key_handler.py
ooodev/adapter/awt/key_handler_events.py
ooodev/adapter/awt/key_listener.py
ooodev/adapter/awt/mouse_click_events.py
ooodev/adapter/awt/mouse_click_handler.py
ooodev/adapter/awt/mouse_events.py
ooodev/adapter/awt/mouse_listener.py
ooodev/adapter/awt/mouse_motion_events.py
ooodev/adapter/awt/mouse_motion_listener.py
ooodev/adapter/awt/paint_events.py
ooodev/adapter/awt/paint_listener.py
ooodev/adapter/awt/spin_events.py
ooodev/adapter/awt/spin_listener.py
ooodev/adapter/awt/tab/__init__.py
ooodev/adapter/awt/tab/tab_page_container_events.py
ooodev/adapter/awt/tab/tab_page_container_listener.py
ooodev/adapter/awt/tab_controller_model_partial.py
ooodev/adapter/awt/text_events.py
ooodev/adapter/awt/text_listener.py
ooodev/adapter/awt/top_window_events.py
ooodev/adapter/awt/top_window_listener.py
ooodev/adapter/awt/top_window_partial.py
ooo_dev_tools-0.28.4.dist-info/LICENSE
ooo_dev_tools-0.28.4.dist-info/METADATA
ooo_dev_tools-0.28.4.dist-info/WHEEL
ooo_dev_tools-0.28.4.dist-info/RECORD
