Metadata-Version: 2.1
Name: ooo-dev-tools
Version: 0.28.4
Summary: LibreOffice Developer Tools
Home-page: https://github.com/Amourspirit/python_ooo_dev_tools
License: Apache Software License
Keywords: ooodev,libreoffice,openoffice,macro,uno,ooouno,pyuno
Author: :Barry-Thomas-Paul: Moss
Author-email: bigbytetech@gmail.com
Requires-Python: >=3.8,<4.0
Classifier: Intended Audience :: Developers
Classifier: License :: OSI Approved :: Apache Software License
Classifier: License :: Other/Proprietary License
Classifier: Operating System :: OS Independent
Classifier: Programming Language :: Python
Classifier: Programming Language :: Python :: 3
Classifier: Programming Language :: Python :: 3.8
Classifier: Programming Language :: Python :: 3.9
Classifier: Programming Language :: Python :: 3.10
Classifier: Programming Language :: Python :: 3.11
Classifier: Programming Language :: Python :: 3.12
Classifier: Topic :: Office/Business
Requires-Dist: ooouno (>=2.1.2)
Requires-Dist: typing-extensions (>=4.9.0)
Project-URL: Documentation, https://python-ooo-dev-tools.readthedocs.io/en/latest/index.html
Project-URL: Repository, https://github.com/Amourspirit/python_ooo_dev_tools
